rstbebe/__init__.py
rstbebe/__main__.py
rstbebe/_checkers.py
rstbebe/_model.py
rstbebe-0.2.0.dist-info/entry_points.txt
rstbebe-0.2.0.dist-info/LICENSE.txt
rstbebe-0.2.0.dist-info/WHEEL
rstbebe-0.2.0.dist-info/METADATA
rstbebe-0.2.0.dist-info/RECORD
