Metadata-Version: 2.3
Name: rstbebe
Version: 0.2.0
Summary: RST baby! Let's go!
Keywords: 
Author-email: Stephen Rosen <sirosen0@gmail.com>
Requires-Python: >=3.9
Classifier: Development Status :: 3 - Alpha
Classifier: Programming Language :: Python
Requires-Dist: docutils
Requires-Dist: click>=8,<9
Project-URL: changelog, https://github.com/sirosen/rstbebe/blob/main/CHANGELOG.md
Project-URL: source, https://github.com/sirosen/rstbebe
